glplotlib/__init__.py
glplotlib/glplot.py
glplotlib/utilites.py
glplotlib-0.1.1.dist-info/LICENSE.txt
glplotlib-0.1.1.dist-info/METADATA
glplotlib-0.1.1.dist-info/WHEEL
glplotlib-0.1.1.dist-info/top_level.txt
glplotlib-0.1.1.dist-info/RECORD
